pymodaq_spectro/__init__.py
pymodaq_spectro/spectrometer.py
pymodaq_spectro/version.py
pymodaq_spectro/utils/__init__.py
pymodaq_spectro/utils/calibration.py
pymodaq_spectro/utils/utils_classes.py
pymodaq_spectro-1.1.1.dist-info/LICENSE
pymodaq_spectro-1.1.1.dist-info/METADATA
pymodaq_spectro-1.1.1.dist-info/WHEEL
pymodaq_spectro-1.1.1.dist-info/top_level.txt
pymodaq_spectro-1.1.1.dist-info/RECORD
