Metadata-Version: 2.1
Name: pymodaq-spectro
Version: 1.1.1
Summary: Spectrometer Interface using PyMoDAQ
Home-page: http://pymodaq.cnrs.fr
Author: Sébastien Weber
Author-email: sebastien.weber@cemes.fr
License: MIT
Platform: UNKNOWN
Classifier: Programming Language :: Python :: 3
Classifier: Development Status :: 5 - Production/Stable
Classifier: Environment :: Other Environment
Classifier: Intended Audience :: Science/Research
Classifier: Topic :: Scientific/Engineering :: Human Machine Interfaces
Classifier: Topic :: Scientific/Engineering :: Visualization
Classifier: License :: OSI Approved :: MIT License
Classifier: Operating System :: OS Independent
Classifier: Topic :: Software Development :: Libraries :: Python Modules
Classifier: Topic :: Software Development :: User Interfaces
License-File: LICENSE
Requires-Dist: pymodaq
Requires-Dist: pandas
Requires-Dist: units-converter
